odoo8_addon_account_bank_statement_import_ofx-8.0.1.0.1.99.dev18-py2.7-nspkg.pth
odoo8_addon_account_bank_statement_import_ofx-8.0.1.0.1.99.dev18.dist-info/METADATA
odoo8_addon_account_bank_statement_import_ofx-8.0.1.0.1.99.dev18.dist-info/RECORD
odoo8_addon_account_bank_statement_import_ofx-8.0.1.0.1.99.dev18.dist-info/WHEEL
odoo8_addon_account_bank_statement_import_ofx-8.0.1.0.1.99.dev18.dist-info/namespace_packages.txt
odoo8_addon_account_bank_statement_import_ofx-8.0.1.0.1.99.dev18.dist-info/top_level.txt
odoo_addons/account_bank_statement_import_ofx/README.rst
odoo_addons/account_bank_statement_import_ofx/__init__.py
odoo_addons/account_bank_statement_import_ofx/__openerp__.py
odoo_addons/account_bank_statement_import_ofx/account_bank_statement_import_ofx.py
odoo_addons/account_bank_statement_import_ofx/demo/demo_data.xml
odoo_addons/account_bank_statement_import_ofx/i18n/account_bank_statement_import_ofx.pot
odoo_addons/account_bank_statement_import_ofx/i18n/de.po
odoo_addons/account_bank_statement_import_ofx/i18n/es.po
odoo_addons/account_bank_statement_import_ofx/i18n/fi.po
odoo_addons/account_bank_statement_import_ofx/i18n/fr.po
odoo_addons/account_bank_statement_import_ofx/i18n/lt_LT.po
odoo_addons/account_bank_statement_import_ofx/i18n/nl.po
odoo_addons/account_bank_statement_import_ofx/i18n/pt_BR.po
odoo_addons/account_bank_statement_import_ofx/i18n/pt_PT.po
odoo_addons/account_bank_statement_import_ofx/i18n/sl.po
odoo_addons/account_bank_statement_import_ofx/static/description/icon.png
odoo_addons/account_bank_statement_import_ofx/test_ofx_file/test_ofx.ofx
odoo_addons/account_bank_statement_import_ofx/tests/__init__.py
odoo_addons/account_bank_statement_import_ofx/tests/test_import_bank_statement.py
